{"interfaceLanguages":{"swift":[{"children":[{"title":"Classes","type":"groupMarker"},{"children":[{"title":"Instance Properties","type":"groupMarker"},{"path":"\/documentation\/twittertexteditor\/configuration\/attributenamesdescribedforattributedstringshortdescription","title":"var attributeNamesDescribedForAttributedStringShortDescription: Set<NSAttributedString.Key>?","type":"property"},{"path":"\/documentation\/twittertexteditor\/configuration\/isattributedstringshortdescriptionforloggingenabled","title":"var isAttributedStringShortDescriptionForLoggingEnabled: Bool","type":"property"},{"path":"\/documentation\/twittertexteditor\/configuration\/isdebuglayoutmanagerdrawglyphsenabled","title":"var isDebugLayoutManagerDrawGlyphsEnabled: Bool","type":"property"},{"path":"\/documentation\/twittertexteditor\/configuration\/logger","title":"var logger: Logger?","type":"property"},{"path":"\/documentation\/twittertexteditor\/configuration\/tracer","title":"var tracer: Tracer?","type":"property"},{"title":"Type Properties","type":"groupMarker"},{"path":"\/documentation\/twittertexteditor\/configuration\/shared","title":"static let shared: Configuration","type":"property"}],"path":"\/documentation\/twittertexteditor\/configuration","title":"Configuration","type":"class"},{"children":[{"title":"Initializers","type":"groupMarker"},{"path":"\/documentation\/twittertexteditor\/texteditorview\/init(frame:)","title":"init(frame: CGRect)","type":"init"},{"title":"Instance Properties","type":"groupMarker"},{"path":"\/documentation\/twittertexteditor\/texteditorview\/canbecomefirstresponder","title":"var canBecomeFirstResponder: Bool","type":"property"},{"path":"\/documentation\/twittertexteditor\/texteditorview\/canresignfirstresponder","title":"var canResignFirstResponder: Bool","type":"property"},{"path":"\/documentation\/twittertexteditor\/texteditorview\/caretrectatbeginningofselectedrange","title":"var caretRectAtBeginningOfSelectedRange: CGRect?","type":"property"},{"path":"\/documentation\/twittertexteditor\/texteditorview\/caretrectatendofselectedrange","title":"var caretRectAtEndOfSelectedRange: CGRect?","type":"property"},{"path":"\/documentation\/twittertexteditor\/texteditorview\/changeobserver","title":"var changeObserver: TextEditorViewChangeObserver?","type":"property"},{"path":"\/documentation\/twittertexteditor\/texteditorview\/defaultlinebreakmode","title":"var defaultLineBreakMode: NSLineBreakMode","type":"property"},{"path":"\/documentation\/twittertexteditor\/texteditorview\/editingcontentdelegate","title":"var editingContentDelegate: TextEditorViewEditingContentDelegate?","type":"property"},{"path":"\/documentation\/twittertexteditor\/texteditorview\/editingdelegate","title":"var editingDelegate: TextEditorViewEditingDelegate?","type":"property"},{"path":"\/documentation\/twittertexteditor\/texteditorview\/font","title":"var font: UIFont?","type":"property"},{"path":"\/documentation\/twittertexteditor\/texteditorview\/inputaccessoryview","title":"var inputAccessoryView: UIView?","type":"property"},{"path":"\/documentation\/twittertexteditor\/texteditorview\/inputaccessoryviewcontroller","title":"var inputAccessoryViewController: UIInputViewController?","type":"property"},{"path":"\/documentation\/twittertexteditor\/texteditorview\/inputprimarylanguage","title":"var inputPrimaryLanguage: String?","type":"property"},{"path":"\/documentation\/twittertexteditor\/texteditorview\/inputview","title":"var inputView: UIView?","type":"property"},{"path":"\/documentation\/twittertexteditor\/texteditorview\/inputviewcontroller","title":"var inputViewController: UIInputViewController?","type":"property"},{"path":"\/documentation\/twittertexteditor\/texteditorview\/isdropinteractionenabled","title":"var isDropInteractionEnabled: Bool","type":"property"},{"path":"\/documentation\/twittertexteditor\/texteditorview\/iseditable","title":"var isEditable: Bool","type":"property"},{"path":"\/documentation\/twittertexteditor\/texteditorview\/isediting","title":"var isEditing: Bool","type":"property"},{"path":"\/documentation\/twittertexteditor\/texteditorview\/isfirstresponder","title":"var isFirstResponder: Bool","type":"property"},{"path":"\/documentation\/twittertexteditor\/texteditorview\/isscrollenabled","title":"var isScrollEnabled: Bool","type":"property"},{"path":"\/documentation\/twittertexteditor\/texteditorview\/isselectable","title":"var isSelectable: Bool","type":"property"},{"path":"\/documentation\/twittertexteditor\/texteditorview\/maximumnumberoflinesforplaceholdertext","title":"var maximumNumberOfLinesForPlaceholderText: Int","type":"property"},{"path":"\/documentation\/twittertexteditor\/texteditorview\/pasteobservers","title":"var pasteObservers: [TextEditorViewPasteObserver]","type":"property"},{"path":"\/documentation\/twittertexteditor\/texteditorview\/placeholdertext","title":"var placeholderText: String?","type":"property"},{"path":"\/documentation\/twittertexteditor\/texteditorview\/placeholdertextcolor","title":"var placeholderTextColor: UIColor?","type":"property"},{"path":"\/documentation\/twittertexteditor\/texteditorview\/placeholdertextlinebreakmode","title":"var placeholderTextLineBreakMode: NSLineBreakMode","type":"property"},{"path":"\/documentation\/twittertexteditor\/texteditorview\/returntoendeditingenabled","title":"var returnToEndEditingEnabled: Bool","type":"property"},{"path":"\/documentation\/twittertexteditor\/texteditorview\/scrollview","title":"var scrollView: UIScrollView","type":"property"},{"path":"\/documentation\/twittertexteditor\/texteditorview\/selectedrange","title":"var selectedRange: NSRange","type":"property"},{"path":"\/documentation\/twittertexteditor\/texteditorview\/text","title":"var text: String","type":"property"},{"path":"\/documentation\/twittertexteditor\/texteditorview\/textalignment","title":"var textAlignment: NSTextAlignment","type":"property"},{"path":"\/documentation\/twittertexteditor\/texteditorview\/textattributesdelegate","title":"var textAttributesDelegate: TextEditorViewTextAttributesDelegate?","type":"property"},{"path":"\/documentation\/twittertexteditor\/texteditorview\/textcolor","title":"var textColor: UIColor?","type":"property"},{"path":"\/documentation\/twittertexteditor\/texteditorview\/textcontentinsets","title":"var textContentInsets: UIEdgeInsets","type":"property"},{"path":"\/documentation\/twittertexteditor\/texteditorview\/textcontentpadding","title":"var textContentPadding: CGFloat","type":"property"},{"path":"\/documentation\/twittertexteditor\/texteditorview\/textcontentview","title":"var textContentView: UIView","type":"property"},{"path":"\/documentation\/twittertexteditor\/texteditorview\/textinputobserver","title":"var textInputObserver: TextEditorViewTextInputObserver?","type":"property"},{"path":"\/documentation\/twittertexteditor\/texteditorview\/tintcolor","title":"var tintColor: UIColor!","type":"property"},{"title":"Instance Methods","type":"groupMarker"},{"path":"\/documentation\/twittertexteditor\/texteditorview\/becomefirstresponder()","title":"func becomeFirstResponder() -> Bool","type":"method"},{"path":"\/documentation\/twittertexteditor\/texteditorview\/didmovetowindow()","title":"func didMoveToWindow()","type":"method"},{"path":"\/documentation\/twittertexteditor\/texteditorview\/isdraggingtext(of:)","title":"func isDraggingText(of: UIDragSession) -> Bool","type":"method"},{"path":"\/documentation\/twittertexteditor\/texteditorview\/reloadinputviews()","title":"func reloadInputViews()","type":"method"},{"path":"\/documentation\/twittertexteditor\/texteditorview\/resignfirstresponder()","title":"func resignFirstResponder() -> Bool","type":"method"},{"path":"\/documentation\/twittertexteditor\/texteditorview\/setneedsupdatetextattributes()","title":"func setNeedsUpdateTextAttributes()","type":"method"},{"path":"\/documentation\/twittertexteditor\/texteditorview\/showmenu()","title":"func showMenu()","type":"method"},{"path":"\/documentation\/twittertexteditor\/texteditorview\/sizethatfits(_:)","title":"func sizeThatFits(CGSize) -> CGSize","type":"method"},{"path":"\/documentation\/twittertexteditor\/texteditorview\/updatebyreplacing(range:with:selectedrange:)","title":"func updateByReplacing(range: NSRange, with: String, selectedRange: NSRange?) throws","type":"method"},{"path":"\/documentation\/twittertexteditor\/texteditorview\/usepreferredtextinputprimarylanguage(_:)","title":"func usePreferredTextInputPrimaryLanguage(String?)","type":"method"},{"title":"Default Implementations","type":"groupMarker"},{"children":[{"title":"Instance Methods","type":"groupMarker"},{"path":"\/documentation\/twittertexteditor\/texteditorview\/textstorage(_:didprocessediting:range:changeinlength:)","title":"func textStorage(NSTextStorage, didProcessEditing: NSTextStorage.EditActions, range: NSRange, changeInLength: Int)","type":"method"},{"path":"\/documentation\/twittertexteditor\/texteditorview\/textstorage(_:willprocessediting:range:changeinlength:)","title":"func textStorage(NSTextStorage, willProcessEditing: NSTextStorage.EditActions, range: NSRange, changeInLength: Int)","type":"method"}],"path":"\/documentation\/twittertexteditor\/texteditorview\/nstextstoragedelegate-implementations","title":"NSTextStorageDelegate Implementations","type":"symbol"},{"children":[{"title":"Instance Methods","type":"groupMarker"},{"path":"\/documentation\/twittertexteditor\/texteditorview\/textpasteconfigurationsupporting(_:canpaste:)","title":"func textPasteConfigurationSupporting(UITextPasteConfigurationSupporting, canPaste: [NSItemProvider]) -> Bool","type":"method"}],"path":"\/documentation\/twittertexteditor\/texteditorview\/textviewtextpastedelegate-implementations","title":"TextViewTextPasteDelegate Implementations","type":"symbol"},{"children":[{"title":"Instance Methods","type":"groupMarker"},{"path":"\/documentation\/twittertexteditor\/texteditorview\/textdraggableview(_:dragsessiondidend:with:)","title":"func textDraggableView(UIView & UITextDraggable, dragSessionDidEnd: UIDragSession, with: UIDropOperation)","type":"method"},{"path":"\/documentation\/twittertexteditor\/texteditorview\/textdraggableview(_:dragsessionwillbegin:)","title":"func textDraggableView(UIView & UITextDraggable, dragSessionWillBegin: UIDragSession)","type":"method"}],"path":"\/documentation\/twittertexteditor\/texteditorview\/uitextdragdelegate-implementations","title":"UITextDragDelegate Implementations","type":"symbol"},{"children":[{"title":"Instance Methods","type":"groupMarker"},{"path":"\/documentation\/twittertexteditor\/texteditorview\/textdroppableview(_:proposalfordrop:)","title":"func textDroppableView(UIView & UITextDroppable, proposalForDrop: UITextDropRequest) -> UITextDropProposal","type":"method"}],"path":"\/documentation\/twittertexteditor\/texteditorview\/uitextdropdelegate-implementations","title":"UITextDropDelegate Implementations","type":"symbol"},{"children":[{"title":"Instance Properties","type":"groupMarker"},{"path":"\/documentation\/twittertexteditor\/texteditorview\/autocapitalizationtype","title":"var autocapitalizationType: UITextAutocapitalizationType","type":"property"},{"path":"\/documentation\/twittertexteditor\/texteditorview\/autocorrectiontype","title":"var autocorrectionType: UITextAutocorrectionType","type":"property"},{"path":"\/documentation\/twittertexteditor\/texteditorview\/enablesreturnkeyautomatically","title":"var enablesReturnKeyAutomatically: Bool","type":"property"},{"path":"\/documentation\/twittertexteditor\/texteditorview\/issecuretextentry","title":"var isSecureTextEntry: Bool","type":"property"},{"path":"\/documentation\/twittertexteditor\/texteditorview\/keyboardappearance","title":"var keyboardAppearance: UIKeyboardAppearance","type":"property"},{"path":"\/documentation\/twittertexteditor\/texteditorview\/keyboardtype","title":"var keyboardType: UIKeyboardType","type":"property"},{"path":"\/documentation\/twittertexteditor\/texteditorview\/passwordrules","title":"var passwordRules: UITextInputPasswordRules?","type":"property"},{"path":"\/documentation\/twittertexteditor\/texteditorview\/returnkeytype","title":"var returnKeyType: UIReturnKeyType","type":"property"},{"path":"\/documentation\/twittertexteditor\/texteditorview\/smartdashestype","title":"var smartDashesType: UITextSmartDashesType","type":"property"},{"path":"\/documentation\/twittertexteditor\/texteditorview\/smartinsertdeletetype","title":"var smartInsertDeleteType: UITextSmartInsertDeleteType","type":"property"},{"path":"\/documentation\/twittertexteditor\/texteditorview\/smartquotestype","title":"var smartQuotesType: UITextSmartQuotesType","type":"property"},{"path":"\/documentation\/twittertexteditor\/texteditorview\/spellcheckingtype","title":"var spellCheckingType: UITextSpellCheckingType","type":"property"},{"path":"\/documentation\/twittertexteditor\/texteditorview\/textcontenttype","title":"var textContentType: UITextContentType!","type":"property"}],"path":"\/documentation\/twittertexteditor\/texteditorview\/uitextinputtraits-implementations","title":"UITextInputTraits Implementations","type":"symbol"},{"children":[{"title":"Instance Methods","type":"groupMarker"},{"path":"\/documentation\/twittertexteditor\/texteditorview\/textpasteconfigurationsupporting(_:shouldanimatepasteof:to:)","title":"func textPasteConfigurationSupporting(UITextPasteConfigurationSupporting, shouldAnimatePasteOf: NSAttributedString, to: UITextRange) -> Bool","type":"method"},{"path":"\/documentation\/twittertexteditor\/texteditorview\/textpasteconfigurationsupporting(_:transform:)","title":"func textPasteConfigurationSupporting(UITextPasteConfigurationSupporting, transform: UITextPasteItem)","type":"method"}],"path":"\/documentation\/twittertexteditor\/texteditorview\/uitextpastedelegate-implementations","title":"UITextPasteDelegate Implementations","type":"symbol"},{"children":[{"title":"Instance Methods","type":"groupMarker"},{"path":"\/documentation\/twittertexteditor\/texteditorview\/textview(_:shouldchangetextin:replacementtext:)","title":"func textView(UITextView, shouldChangeTextIn: NSRange, replacementText: String) -> Bool","type":"method"},{"path":"\/documentation\/twittertexteditor\/texteditorview\/textviewdidbeginediting(_:)","title":"func textViewDidBeginEditing(UITextView)","type":"method"},{"path":"\/documentation\/twittertexteditor\/texteditorview\/textviewdidchange(_:)","title":"func textViewDidChange(UITextView)","type":"method"},{"path":"\/documentation\/twittertexteditor\/texteditorview\/textviewdidchangeselection(_:)","title":"func textViewDidChangeSelection(UITextView)","type":"method"},{"path":"\/documentation\/twittertexteditor\/texteditorview\/textviewdidendediting(_:)","title":"func textViewDidEndEditing(UITextView)","type":"method"},{"path":"\/documentation\/twittertexteditor\/texteditorview\/textviewshouldbeginediting(_:)","title":"func textViewShouldBeginEditing(UITextView) -> Bool","type":"method"}],"path":"\/documentation\/twittertexteditor\/texteditorview\/uitextviewdelegate-implementations","title":"UITextViewDelegate Implementations","type":"symbol"}],"path":"\/documentation\/twittertexteditor\/texteditorview","title":"TextEditorView","type":"class"},{"title":"Protocols","type":"groupMarker"},{"children":[{"title":"Instance Methods","type":"groupMarker"},{"path":"\/documentation\/twittertexteditor\/logger\/log(type:file:line:function:message:)","title":"func log(type: LogType, file: StaticString, line: Int, function: StaticString, message: () -> String?)","type":"method"}],"path":"\/documentation\/twittertexteditor\/logger","title":"Logger","type":"protocol"},{"children":[{"title":"Instance Methods","type":"groupMarker"},{"path":"\/documentation\/twittertexteditor\/signpost\/begin()","title":"func begin()","type":"method"},{"path":"\/documentation\/twittertexteditor\/signpost\/end()","title":"func end()","type":"method"},{"path":"\/documentation\/twittertexteditor\/signpost\/event()","title":"func event()","type":"method"}],"path":"\/documentation\/twittertexteditor\/signpost","title":"Signpost","type":"protocol"},{"children":[{"title":"Instance Methods","type":"groupMarker"},{"path":"\/documentation\/twittertexteditor\/texteditorviewchangeobserver\/texteditorview(_:didchangewithchangeresult:)","title":"func textEditorView(TextEditorView, didChangeWithChangeResult: TextEditorViewChangeResult)","type":"method"}],"path":"\/documentation\/twittertexteditor\/texteditorviewchangeobserver","title":"TextEditorViewChangeObserver","type":"protocol"},{"children":[{"title":"Instance Properties","type":"groupMarker"},{"path":"\/documentation\/twittertexteditor\/texteditorviewchangeresult\/isselectedrangechanged","title":"var isSelectedRangeChanged: Bool","type":"property"},{"path":"\/documentation\/twittertexteditor\/texteditorviewchangeresult\/istextchanged","title":"var isTextChanged: Bool","type":"property"}],"path":"\/documentation\/twittertexteditor\/texteditorviewchangeresult","title":"TextEditorViewChangeResult","type":"protocol"},{"children":[{"title":"Instance Properties","type":"groupMarker"},{"path":"\/documentation\/twittertexteditor\/texteditorvieweditingcontent\/selectedrange","title":"var selectedRange: NSRange","type":"property"},{"path":"\/documentation\/twittertexteditor\/texteditorvieweditingcontent\/text","title":"var text: String","type":"property"}],"path":"\/documentation\/twittertexteditor\/texteditorvieweditingcontent","title":"TextEditorViewEditingContent","type":"protocol"},{"children":[{"title":"Instance Methods","type":"groupMarker"},{"path":"\/documentation\/twittertexteditor\/texteditorvieweditingcontentdelegate\/texteditorview(_:updateeditingcontent:)","title":"func textEditorView(TextEditorView, updateEditingContent: TextEditorViewEditingContent) -> TextEditorViewEditingContent?","type":"method"}],"path":"\/documentation\/twittertexteditor\/texteditorvieweditingcontentdelegate","title":"TextEditorViewEditingContentDelegate","type":"protocol"},{"children":[{"title":"Instance Methods","type":"groupMarker"},{"path":"\/documentation\/twittertexteditor\/texteditorvieweditingdelegate\/texteditorviewdidbeginediting(_:)","title":"func textEditorViewDidBeginEditing(TextEditorView)","type":"method"},{"path":"\/documentation\/twittertexteditor\/texteditorvieweditingdelegate\/texteditorviewdidendediting(_:)","title":"func textEditorViewDidEndEditing(TextEditorView)","type":"method"},{"path":"\/documentation\/twittertexteditor\/texteditorvieweditingdelegate\/texteditorviewshouldbeginediting(_:)","title":"func textEditorViewShouldBeginEditing(TextEditorView) -> Bool","type":"method"}],"path":"\/documentation\/twittertexteditor\/texteditorvieweditingdelegate","title":"TextEditorViewEditingDelegate","type":"protocol"},{"children":[{"title":"Instance Properties","type":"groupMarker"},{"path":"\/documentation\/twittertexteditor\/texteditorviewpasteobserver\/acceptabletypeidentifiers","title":"var acceptableTypeIdentifiers: [String]","type":"property"},{"title":"Instance Methods","type":"groupMarker"},{"path":"\/documentation\/twittertexteditor\/texteditorviewpasteobserver\/canpasteitemprovider(_:)","title":"func canPasteItemProvider(NSItemProvider) -> Bool","type":"method"},{"path":"\/documentation\/twittertexteditor\/texteditorviewpasteobserver\/transformitemprovider(_:completion:)","title":"func transformItemProvider(NSItemProvider, completion: TextEditorViewPasteObserverTransformCompletion)","type":"method"}],"path":"\/documentation\/twittertexteditor\/texteditorviewpasteobserver","title":"TextEditorViewPasteObserver","type":"protocol"},{"children":[{"title":"Instance Methods","type":"groupMarker"},{"path":"\/documentation\/twittertexteditor\/texteditorviewpasteobservertransformcompletion\/notransform()","title":"func noTransform()","type":"method"},{"path":"\/documentation\/twittertexteditor\/texteditorviewpasteobservertransformcompletion\/transformed()","title":"func transformed()","type":"method"},{"path":"\/documentation\/twittertexteditor\/texteditorviewpasteobservertransformcompletion\/transformed(to:)","title":"func transformed(to: String)","type":"method"}],"path":"\/documentation\/twittertexteditor\/texteditorviewpasteobservertransformcompletion","title":"TextEditorViewPasteObserverTransformCompletion","type":"protocol"},{"children":[{"title":"Instance Methods","type":"groupMarker"},{"path":"\/documentation\/twittertexteditor\/texteditorviewtextattributesdelegate\/texteditorview(_:updateattributedstring:completion:)","title":"func textEditorView(TextEditorView, updateAttributedString: NSAttributedString, completion: (NSAttributedString?) -> Void)","type":"method"}],"path":"\/documentation\/twittertexteditor\/texteditorviewtextattributesdelegate","title":"TextEditorViewTextAttributesDelegate","type":"protocol"},{"children":[{"title":"Instance Methods","type":"groupMarker"},{"path":"\/documentation\/twittertexteditor\/texteditorviewtextinputobserver\/texteditorview(_:didchangebasewritingdirection:)","title":"func textEditorView(TextEditorView, didChangeBaseWritingDirection: NSWritingDirection)","type":"method"},{"path":"\/documentation\/twittertexteditor\/texteditorviewtextinputobserver\/texteditorview(_:didchangeinputprimarylanguage:)","title":"func textEditorView(TextEditorView, didChangeInputPrimaryLanguage: String?)","type":"method"}],"path":"\/documentation\/twittertexteditor\/texteditorviewtextinputobserver","title":"TextEditorViewTextInputObserver","type":"protocol"},{"children":[{"title":"Instance Methods","type":"groupMarker"},{"path":"\/documentation\/twittertexteditor\/tracer\/signpost(name:file:line:function:message:)","title":"func signpost(name: StaticString, file: StaticString, line: Int, function: StaticString, message: () -> String?) -> Signpost","type":"method"}],"path":"\/documentation\/twittertexteditor\/tracer","title":"Tracer","type":"protocol"},{"title":"Enumerations","type":"groupMarker"},{"children":[{"title":"Enumeration Cases","type":"groupMarker"},{"path":"\/documentation\/twittertexteditor\/logtype\/debug","title":"case debug","type":"case"},{"path":"\/documentation\/twittertexteditor\/logtype\/default","title":"case `default`","type":"case"},{"path":"\/documentation\/twittertexteditor\/logtype\/error","title":"case error","type":"case"},{"path":"\/documentation\/twittertexteditor\/logtype\/fault","title":"case fault","type":"case"},{"path":"\/documentation\/twittertexteditor\/logtype\/info","title":"case info","type":"case"},{"title":"Default Implementations","type":"groupMarker"},{"children":[{"title":"Operators","type":"groupMarker"},{"path":"\/documentation\/twittertexteditor\/logtype\/!=(_:_:)","title":"static func != (Self, Self) -> Bool","type":"op"}],"path":"\/documentation\/twittertexteditor\/logtype\/equatable-implementations","title":"Equatable Implementations","type":"symbol"}],"path":"\/documentation\/twittertexteditor\/logtype","title":"LogType","type":"enum"},{"children":[{"title":"Classes","type":"groupMarker"},{"children":[{"title":"Initializers","type":"groupMarker"},{"path":"\/documentation\/twittertexteditor\/textattributes\/suffixedattachment\/init(size:attachment:)","title":"init(size: CGSize, attachment: Attachment)","type":"init"},{"title":"Instance Properties","type":"groupMarker"},{"path":"\/documentation\/twittertexteditor\/textattributes\/suffixedattachment\/attachment-swift.property","title":"let attachment: Attachment","type":"property"},{"path":"\/documentation\/twittertexteditor\/textattributes\/suffixedattachment\/description","title":"var description: String","type":"property"},{"path":"\/documentation\/twittertexteditor\/textattributes\/suffixedattachment\/size","title":"let size: CGSize","type":"property"},{"title":"Type Properties","type":"groupMarker"},{"path":"\/documentation\/twittertexteditor\/textattributes\/suffixedattachment\/attributename","title":"static let attributeName: NSAttributedString.Key","type":"property"},{"title":"Enumerations","type":"groupMarker"},{"children":[{"title":"Enumeration Cases","type":"groupMarker"},{"path":"\/documentation\/twittertexteditor\/textattributes\/suffixedattachment\/attachment-swift.enum\/image(_:)","title":"case image(UIImage)","type":"case"},{"path":"\/documentation\/twittertexteditor\/textattributes\/suffixedattachment\/attachment-swift.enum\/view(view:layoutintextcontainer:)","title":"case view(view: UIView, layoutInTextContainer: (UIView, CGRect) -> Void)","type":"case"}],"path":"\/documentation\/twittertexteditor\/textattributes\/suffixedattachment\/attachment-swift.enum","title":"TextAttributes.SuffixedAttachment.Attachment","type":"enum"}],"path":"\/documentation\/twittertexteditor\/textattributes\/suffixedattachment","title":"TextAttributes.SuffixedAttachment","type":"class"}],"path":"\/documentation\/twittertexteditor\/textattributes","title":"TextAttributes","type":"enum"}],"path":"\/documentation\/twittertexteditor","title":"TwitterTextEditor","type":"module"}]},"schemaVersion":{"major":0,"minor":1,"patch":0}}